Metadata-Version: 2.1
Name: metagpt
Version: 0.8.2
Summary: The Multi-Agent Framework
Home-page: https://github.com/geekan/MetaGPT
Author: Alexander Wu
Author-email: alexanderwu@deepwisdom.ai
License: MIT
Keywords: metagpt multi-agent multi-role programming gpt llm metaprogramming
Requires-Python: >=3.9, <3.12
License-File: LICENSE
Requires-Dist: aiohttp==3.8.6
Requires-Dist: channels==4.0.0
Requires-Dist: faiss-cpu==1.7.4
Requires-Dist: fire==0.4.0
Requires-Dist: typer==0.9.0
Requires-Dist: lancedb==0.4.0
Requires-Dist: loguru==0.6.0
Requires-Dist: meilisearch==0.21.0
Requires-Dist: numpy~=1.26.4
Requires-Dist: openai~=1.39.0
Requires-Dist: openpyxl~=3.1.5
Requires-Dist: beautifulsoup4==4.12.3
Requires-Dist: pandas==2.1.1
Requires-Dist: pydantic>=2.5.3
Requires-Dist: python-docx==0.8.11
Requires-Dist: PyYAML==6.0.1
Requires-Dist: setuptools==65.6.3
Requires-Dist: tenacity==8.2.3
Requires-Dist: tiktoken==0.7.0
Requires-Dist: tqdm==4.66.2
Requires-Dist: anthropic==0.18.1
Requires-Dist: typing-inspect==0.8.0
Requires-Dist: libcst==1.0.1
Requires-Dist: qdrant-client==1.7.0
Requires-Dist: grpcio~=1.67.0
Requires-Dist: grpcio-tools~=1.62.3
Requires-Dist: grpcio-status~=1.62.3
Requires-Dist: ta==0.10.2
Requires-Dist: semantic-kernel==0.4.3.dev0
Requires-Dist: wrapt==1.15.0
Requires-Dist: redis~=5.0.0
Requires-Dist: curl-cffi~=0.7.0
Requires-Dist: httplib2~=0.22.0
Requires-Dist: websocket-client~=1.8.0
Requires-Dist: aiofiles==23.2.1
Requires-Dist: gitpython==3.1.40
Requires-Dist: zhipuai~=2.1.5
Requires-Dist: rich==13.6.0
Requires-Dist: nbclient==0.9.0
Requires-Dist: nbformat==5.9.2
Requires-Dist: ipython==8.17.2
Requires-Dist: ipykernel==6.27.1
Requires-Dist: scikit-learn==1.3.2
Requires-Dist: typing-extensions==4.9.0
Requires-Dist: socksio~=1.0.0
Requires-Dist: gitignore-parser==0.1.9
Requires-Dist: websockets<12.0,>=10.0
Requires-Dist: networkx~=3.2.1
Requires-Dist: google-generativeai==0.4.1
Requires-Dist: playwright>=1.26
Requires-Dist: anytree
Requires-Dist: ipywidgets==8.1.1
Requires-Dist: Pillow
Requires-Dist: imap-tools==1.5.0
Requires-Dist: qianfan~=0.4.4
Requires-Dist: dashscope~=1.19.3
Requires-Dist: rank-bm25==0.2.2
Requires-Dist: jieba==0.42.1
Requires-Dist: volcengine-python-sdk[ark]~=1.0.94
Requires-Dist: gymnasium==0.29.1
Requires-Dist: boto3~=1.34.69
Requires-Dist: spark-ai-python~=0.3.30
Requires-Dist: agentops
Requires-Dist: tree-sitter~=0.23.2
Requires-Dist: tree-sitter-python~=0.23.2
Requires-Dist: httpx==0.27.2
Provides-Extra: android_assistant
Requires-Dist: pyshine==0.0.9; extra == "android-assistant"
Requires-Dist: opencv-python==4.6.0.66; extra == "android-assistant"
Requires-Dist: protobuf<3.20,>=3.9.2; extra == "android-assistant"
Requires-Dist: modelscope; extra == "android-assistant"
Requires-Dist: keras==2.9.0; extra == "android-assistant"
Requires-Dist: torch; extra == "android-assistant"
Requires-Dist: torchvision; extra == "android-assistant"
Requires-Dist: transformers; extra == "android-assistant"
Requires-Dist: opencv-python; extra == "android-assistant"
Requires-Dist: matplotlib; extra == "android-assistant"
Requires-Dist: pycocotools; extra == "android-assistant"
Requires-Dist: SentencePiece; extra == "android-assistant"
Requires-Dist: tf-slim; extra == "android-assistant"
Requires-Dist: tf-keras; extra == "android-assistant"
Requires-Dist: pyclipper; extra == "android-assistant"
Requires-Dist: shapely; extra == "android-assistant"
Requires-Dist: groundingdino-py; extra == "android-assistant"
Requires-Dist: datasets==2.18.0; extra == "android-assistant"
Requires-Dist: clip-openai; extra == "android-assistant"
Requires-Dist: tensorflow-macos==2.9; os_name == "darwin" and extra == "android_assistant"
Requires-Dist: tensorflow==2.9.1; os_name == "linux" and extra == "android_assistant"
Requires-Dist: tensorflow==2.9.1; os_name == "win32" and extra == "android_assistant"
Provides-Extra: dev
Requires-Dist: pylint~=3.0.3; extra == "dev"
Requires-Dist: black~=23.3.0; extra == "dev"
Requires-Dist: isort~=5.12.0; extra == "dev"
Requires-Dist: pre-commit~=3.6.0; extra == "dev"
Provides-Extra: pyppeteer
Requires-Dist: pyppeteer>=1.0.2; extra == "pyppeteer"
Provides-Extra: rag
Requires-Dist: llama-index-core==0.10.15; extra == "rag"
Requires-Dist: llama-index-embeddings-azure-openai==0.1.6; extra == "rag"
Requires-Dist: llama-index-embeddings-openai==0.1.5; extra == "rag"
Requires-Dist: llama-index-embeddings-gemini==0.1.6; extra == "rag"
Requires-Dist: llama-index-embeddings-ollama==0.1.2; extra == "rag"
Requires-Dist: llama-index-llms-azure-openai==0.1.4; extra == "rag"
Requires-Dist: llama-index-readers-file==0.1.4; extra == "rag"
Requires-Dist: llama-index-retrievers-bm25==0.1.3; extra == "rag"
Requires-Dist: llama-index-vector-stores-faiss==0.1.1; extra == "rag"
Requires-Dist: llama-index-vector-stores-elasticsearch==0.1.6; extra == "rag"
Requires-Dist: llama-index-vector-stores-chroma==0.1.6; extra == "rag"
Requires-Dist: llama-index-postprocessor-cohere-rerank==0.1.4; extra == "rag"
Requires-Dist: llama-index-postprocessor-colbert-rerank==0.1.1; extra == "rag"
Requires-Dist: llama-index-postprocessor-flag-embedding-reranker==0.1.2; extra == "rag"
Requires-Dist: docx2txt==0.8; extra == "rag"
Provides-Extra: search-ddg
Requires-Dist: duckduckgo-search~=4.1.1; extra == "search-ddg"
Provides-Extra: search-google
Requires-Dist: google-api-python-client==2.94.0; extra == "search-google"
Provides-Extra: selenium
Requires-Dist: selenium>4; extra == "selenium"
Requires-Dist: webdriver-manager; extra == "selenium"
Requires-Dist: beautifulsoup4; extra == "selenium"
Provides-Extra: test
Requires-Dist: llama-index-postprocessor-colbert-rerank==0.1.1; extra == "test"
Requires-Dist: llama-index-embeddings-gemini==0.1.6; extra == "test"
Requires-Dist: llama-index-retrievers-bm25==0.1.3; extra == "test"
Requires-Dist: llama-index-embeddings-azure-openai==0.1.6; extra == "test"
Requires-Dist: webdriver-manager; extra == "test"
Requires-Dist: beautifulsoup4; extra == "test"
Requires-Dist: duckduckgo-search~=4.1.1; extra == "test"
Requires-Dist: llama-index-vector-stores-elasticsearch==0.1.6; extra == "test"
Requires-Dist: llama-index-vector-stores-chroma==0.1.6; extra == "test"
Requires-Dist: docx2txt==0.8; extra == "test"
Requires-Dist: llama-index-postprocessor-cohere-rerank==0.1.4; extra == "test"
Requires-Dist: selenium>4; extra == "test"
Requires-Dist: llama-index-llms-azure-openai==0.1.4; extra == "test"
Requires-Dist: llama-index-vector-stores-faiss==0.1.1; extra == "test"
Requires-Dist: llama-index-readers-file==0.1.4; extra == "test"
Requires-Dist: llama-index-postprocessor-flag-embedding-reranker==0.1.2; extra == "test"
Requires-Dist: llama-index-embeddings-openai==0.1.5; extra == "test"
Requires-Dist: llama-index-embeddings-ollama==0.1.2; extra == "test"
Requires-Dist: llama-index-core==0.10.15; extra == "test"
Requires-Dist: google-api-python-client==2.94.0; extra == "test"
Requires-Dist: pytest; extra == "test"
Requires-Dist: pytest-asyncio; extra == "test"
Requires-Dist: pytest-cov; extra == "test"
Requires-Dist: pytest-mock; extra == "test"
Requires-Dist: pytest-html; extra == "test"
Requires-Dist: pytest-xdist; extra == "test"
Requires-Dist: pytest-timeout; extra == "test"
Requires-Dist: connexion[uvicorn]~=3.0.5; extra == "test"
Requires-Dist: azure-cognitiveservices-speech~=1.31.0; extra == "test"
Requires-Dist: aioboto3~=12.4.0; extra == "test"
Requires-Dist: gradio==3.0.0; extra == "test"
Requires-Dist: google-api-core==2.17.1; extra == "test"
Requires-Dist: protobuf~=4.25.5; extra == "test"
Requires-Dist: pylint==3.0.3; extra == "test"
Requires-Dist: pybrowsers; extra == "test"
